[{"year":2001,"amount":1103},{"year":2002,"amount":1105},{"year":2003,"amount":1102},{"year":2004,"amount":1106},{"year":2005,"amount":1115},{"year":2006,"amount":1111},{"year":2007,"amount":1108},{"year":2008,"amount":1118},{"year":2009,"amount":1121},{"year":2010,"amount":1114},{"year":2011,"amount":1126},{"year":2012,"amount":1122},{"year":2013,"amount":1117},{"year":2014,"amount":1123},{"year":2015,"amount":1124},{"year":2016,"amount":1122},{"year":2017,"amount":1137},{"year":2018,"amount":1128},{"year":2019,"amount":1140},{"year":2020,"amount":1128}]